jobspy_mcp_server/__init__.py
jobspy_mcp_server/server.py
jobspy_mcp_server-1.0.0.dist-info/METADATA
jobspy_mcp_server-1.0.0.dist-info/WHEEL
jobspy_mcp_server-1.0.0.dist-info/entry_points.txt
jobspy_mcp_server-1.0.0.dist-info/licenses/LICENSE
jobspy_mcp_server-1.0.0.dist-info/RECORD
