Metadata-Version: 2.4
Name: jobspy-mcp-server
Version: 1.0.0
Summary: MCP server for JobSpy job scraping library
Project-URL: Homepage, https://github.com/yourorg/jobspy-mcp-server
Project-URL: Source, https://github.com/yourorg/jobspy-mcp-server
Author-email: JobSpy MCP <jobspy@example.com>
License: MIT License
License-File: LICENSE
Keywords: jobs,jobspy,mcp,scraping,server
Classifier: Framework :: FastAPI
Classifier: License :: OSI Approved :: MIT License
Classifier: Operating System :: OS Independent
Classifier: Programming Language :: Python :: 3 :: Only
Classifier: Topic :: Internet :: WWW/HTTP
Requires-Python: >=3.10
Requires-Dist: fastmcp>=0.2.0
Requires-Dist: jobspy>=1.1.82
Requires-Dist: mcp>=1.1.0
Requires-Dist: pandas>=2.1.0
Requires-Dist: pydantic>=2.0.0
Provides-Extra: dev
Requires-Dist: black>=23.0.0; extra == 'dev'
Requires-Dist: mypy>=1.0.0; extra == 'dev'
Requires-Dist: pre-commit>=3.0.0; extra == 'dev'
Requires-Dist: pytest>=7.0.0; extra == 'dev'
